{
    "currentServerUserId":"27",
	
	"jsonCategories": [
        
            {
                "categoryName": "FRUITS & LEGUMES DE LUXE",
                "color": "2131099751",
                "icon": "2131230867",
                "sync": "1",
                "email": "karimamrani0909@gmail.com",
				"categoryId":"1",
				"crud_status":"0"

            },
            {
                "categoryName": "CATEGORIE DE LUXE",
                "color": "2131099751",
                "icon": "2131230867",
                "sync": "1",
                "email": "karimamrani0909@gmail.com",
				"categoryId":"2",
				"crud_status":"0"
            }

        ]
		
}
